rangebar/CLAUDE.md
rangebar/__init__.py
rangebar/__init__.pyi
rangebar/_core.cpython-313-x86_64-linux-gnu.so
rangebar/checkpoint.py
rangebar/cli.py
rangebar/clickhouse/CLAUDE.md
rangebar/clickhouse/__init__.py
rangebar/clickhouse/bulk_operations.py
rangebar/clickhouse/cache.py
rangebar/clickhouse/client.py
rangebar/clickhouse/config.py
rangebar/clickhouse/mixin.py
rangebar/clickhouse/preflight.py
rangebar/clickhouse/query_operations.py
rangebar/clickhouse/schema.sql
rangebar/clickhouse/tunnel.py
rangebar/constants.py
rangebar/conversion.py
rangebar/exceptions.py
rangebar/exness.py
rangebar/hooks.py
rangebar/logging.py
rangebar/notify/__init__.py
rangebar/notify/pushover.py
rangebar/notify/telegram.py
rangebar/orchestration/__init__.py
rangebar/orchestration/count_bounded.py
rangebar/orchestration/helpers.py
rangebar/orchestration/models.py
rangebar/orchestration/precompute.py
rangebar/orchestration/range_bars.py
rangebar/orchestration/tick_fetcher.py
rangebar/ouroboros.py
rangebar/processors/__init__.py
rangebar/processors/api.py
rangebar/processors/core.py
rangebar/resource_guard.py
rangebar/storage/__init__.py
rangebar/storage/checksum_registry.py
rangebar/storage/parquet.py
rangebar/streaming.py
rangebar/validation/__init__.py
rangebar/validation/cache_staleness.py
rangebar/validation/continuity.py
rangebar/validation/gap_classification.py
rangebar/validation/post_storage.py
rangebar/validation/tier1.py
rangebar/validation/tier2.py
rangebar-11.4.0.dist-info/METADATA
rangebar-11.4.0.dist-info/WHEEL
rangebar-11.4.0.dist-info/entry_points.txt
rangebar-11.4.0.dist-info/licenses/LICENSE
rangebar.libs/libcom_err-2abe824b.so.2
rangebar.libs/libcrypto-d3570994.so.10
rangebar.libs/libgssapi_krb5-497db0c6.so.2
rangebar.libs/libk5crypto-b1f99d5c.so.3
rangebar.libs/libkeyutils-dfe70bd6.so.1
rangebar.libs/libkrb5-fcafa220.so.3
rangebar.libs/libkrb5support-d0bcff84.so.0
rangebar.libs/libpcre-9513aab5.so.1
rangebar.libs/libselinux-0922c95c.so.1
rangebar.libs/libssl-cd1d6220.so.10
rangebar-11.4.0.dist-info/RECORD
