Metadata-Version: 2.4
Name: rangebar
Version: 11.4.0
Classifier: Development Status :: 4 - Beta
Classifier: Intended Audience :: Financial and Insurance Industry
Classifier: License :: OSI Approved :: MIT License
Classifier: Programming Language :: Python :: 3.13
Classifier: Programming Language :: Rust
Classifier: Topic :: Office/Business :: Financial :: Investment
Requires-Dist: pandas>=2.0
Requires-Dist: numpy>=1.24
Requires-Dist: polars>=1.0
Requires-Dist: pyarrow>=14.0
Requires-Dist: platformdirs>=4.0
Requires-Dist: clickhouse-connect>=0.8
Requires-Dist: arro3-core>=0.6.5
Requires-Dist: click>=8.0
Requires-Dist: requests>=2.28
Requires-Dist: loguru>=0.7.0
Requires-Dist: backtesting>=0.3 ; extra == 'backtesting'
Requires-Dist: pytest>=7.0 ; extra == 'dev'
Requires-Dist: pytest-benchmark>=4.0 ; extra == 'dev'
Requires-Dist: mypy>=1.0 ; extra == 'dev'
Requires-Dist: black>=23.0 ; extra == 'dev'
Requires-Dist: ruff>=0.1 ; extra == 'dev'
Provides-Extra: backtesting
Provides-Extra: dev
Provides-Extra: exness
License-File: LICENSE
Summary: Python bindings for rangebar: Non-lookahead range bar construction for cryptocurrency trading
Keywords: trading,cryptocurrency,range-bars,backtesting,technical-analysis
Author: Terry Li
License: MIT
Requires-Python: >=3.13
Project-URL: Documentation, https://github.com/terrylica/rangebar-py#readme
Project-URL: Repository, https://github.com/terrylica/rangebar-py
Project-URL: Upstream (Rust), https://github.com/terrylica/rangebar
